iced_x86-1.21.0.dist-info/WHEEL
iced_x86-1.21.0.dist-info/LICENSE.txt
iced_x86-1.21.0.dist-info/RECORD
iced_x86-1.21.0.dist-info/top_level.txt
iced_x86-1.21.0.dist-info/METADATA
iced_x86/EncodingKind.py
iced_x86/CC_e.py
iced_x86/CC_p.py
iced_x86/OpCodeOperandKind.py
iced_x86/Mnemonic.py
iced_x86/ConditionCode.py
iced_x86/CC_be.py
iced_x86/DecoderOptions.py
iced_x86/CC_ae.py
iced_x86/MvexRegMemConv.py
iced_x86/RflagsBits.py
iced_x86/DecoderError.py
iced_x86/CC_g.py
iced_x86/CpuidFeature.py
iced_x86/FormatterSyntax.py
iced_x86/CC_le.py
iced_x86/CC_np.py
iced_x86/OpAccess.py
iced_x86/MandatoryPrefix.py
iced_x86/MemorySizeOptions.py
iced_x86/CodeSize.py
iced_x86/Code.py
iced_x86/__init__.py
iced_x86/CC_ge.py
iced_x86/CC_ne.py
iced_x86/Register.py
iced_x86/FlowControl.py
iced_x86/TupleType.py
iced_x86/_iced_x86_py.pyi
iced_x86/CC_a.py
iced_x86/MvexEHBit.py
iced_x86/CC_l.py
iced_x86/OpKind.py
iced_x86/MemorySize.py
iced_x86/CC_b.py
iced_x86/_iced_x86_py.abi3.so
iced_x86/RepPrefixKind.py
iced_x86/FormatMnemonicOptions.py
iced_x86/MvexTupleTypeLutKind.py
iced_x86/RoundingControl.py
iced_x86/OpCodeTableKind.py
iced_x86/py.typed
iced_x86/MvexConvFn.py
