Metadata-Version: 2.1
Name: iced-x86
Version: 1.21.0
Summary: iced-x86 is a blazing fast and correct x86/x64 disassembler, assembler and instruction decoder
Home-page: https://github.com/icedland/iced/tree/master/src/rust/iced-x86-py
Author: wtfsck
Author-email: wtfsck@protonmail.com
License: MIT
Platform: any
Classifier: Development Status :: 5 - Production/Stable
Classifier: Intended Audience :: Developers
Classifier: License :: OSI Approved :: MIT License
Classifier: Operating System :: MacOS :: MacOS X
Classifier: Operating System :: Microsoft :: Windows
Classifier: Operating System :: OS Independent
Classifier: Operating System :: POSIX
Classifier: Programming Language :: Python
Classifier: Programming Language :: Python :: 3
Classifier: Programming Language :: Python :: 3.8
Classifier: Programming Language :: Python :: 3.9
Classifier: Programming Language :: Python :: 3.10
Classifier: Programming Language :: Python :: 3.11
Classifier: Programming Language :: Python :: Implementation :: CPython
Classifier: Programming Language :: Python :: Implementation :: PyPy
Classifier: Programming Language :: Rust
Classifier: Topic :: Software Development :: Disassemblers
Classifier: Topic :: Software Development :: Libraries
Requires-Python: ~=3.8
License-File: LICENSE.txt
